LICENCE
MANIFEST.in
README.md
README.rst
setup.py
django_follow.egg-info/PKG-INFO
django_follow.egg-info/SOURCES.txt
django_follow.egg-info/dependency_links.txt
django_follow.egg-info/not-zip-safe
django_follow.egg-info/top_level.txt
example/__init__.py
example/manage.py
example/settings.py
example/urls.py
example/app/__init__.py
example/app/models.py
example/app/tests.py
example/app/views.py
follow/__init__.py
follow/admin.py
follow/models.py
follow/registry.py
follow/signals.py
follow/tests.py
follow/urls.py
follow/utils.py
follow/views.py
follow/templates/follow/form.html
follow/templatetags/__init__.py
follow/templatetags/follow_tags.py