Metadata-Version: 1.0
Name: django-follow
Version: 0.6
Summary: Application which enables following features for users. Can be used for contact books or whatnot
Home-page: https://github.com/caffeinehit/django-follow
Author: Alen Mujezinovic
Author-email: alen@caffeinehit.com
License: UNKNOWN
Platform: UNKNOWN
